fdbk/__init__.py
fdbk/_client_connection.py
fdbk/_db_connection.py
fdbk/_dict_connection.py
fdbk/_version.py
fdbk/reporter.py
fdbk/validate.py
fdbk/builtin/__init__.py
fdbk/builtin/_console_utils.py
fdbk/builtin/parallel_exec.py
fdbk/data_tools/__init__.py
fdbk/data_tools/_aggregate.py
fdbk/data_tools/_process.py
fdbk/data_tools/_run.py
fdbk/data_tools/functions/__init__.py
fdbk/data_tools/functions/_chart_funcs.py
fdbk/data_tools/functions/_collection_funcs.py
fdbk/data_tools/functions/_status_funcs.py
fdbk/data_tools/functions/_value_funcs.py
fdbk/data_tools/functions/utils.py
fdbk/schemas/__init__.py
fdbk/schemas/statistics-out.json
fdbk/schemas/topic.json
fdbk/server/__init__.py
fdbk/server/_server.py
fdbk/server/_server_handlers.py
fdbk/utils/__init__.py
fdbk/utils/_common_tests.py
fdbk/utils/_connection.py
fdbk/utils/_format.py
fdbk/utils/_reporter.py
fdbk/utils/messages.py
fdbk-3.4.1.data/scripts/fdbk-server
fdbk-3.4.1.dist-info/LICENSE
fdbk-3.4.1.dist-info/METADATA
fdbk-3.4.1.dist-info/WHEEL
fdbk-3.4.1.dist-info/top_level.txt
fdbk-3.4.1.dist-info/RECORD
