Metadata-Version: 2.1
Name: fdbk
Version: 3.4.1
Summary: Backend and DB wrapper for feedback collection system
Home-page: https://github.com/kangasta/fdbk
Author: Toni Kangas
License: UNKNOWN
Platform: UNKNOWN
Classifier: Programming Language :: Python :: 3
Classifier: License :: OSI Approved :: MIT License
Classifier: Operating System :: OS Independent
Requires-Python: >=3.6
Requires-Dist: jsonschema
Requires-Dist: flask
Requires-Dist: python-dateutil
Requires-Dist: requests
Requires-Dist: importlib-resources ; python_version < "3.7"
